{
    "IND": {
        "2000": {
            "CDA": 0.0520902270581267,
            "NOE": 0,
            "VOE": 0,
            "HAD": 5349.21941895291,
            "COE": 0,
            "NDA": 0.0227884800739593,
            "PMD": 1995.69318381674,
            "OZD": 276.063618063625,
            "SOE": 0,
            "GDP": 476610.0,
            "GDPPC": 449.787,
            "Population": 1059.63
        },
        "2001": {
            "CDA": 0.047497906733414,
            "NOE": 0,
            "VOE": 0,
            "HAD": 5179.85171799336,
            "COE": 0,
            "NDA": 0.0199624512929915,
            "PMD": 2032.41923878174,
            "OZD": 275.854031180305,
            "SOE": 0,
            "GDP": 493953.0,
            "GDPPC": 457.8,
            "Population": 1078.97
        },
        "2002": {
            "CDA": 0.042294287965071,
            "NOE": 0,
            "VOE": 0,
            "HAD": 4992.61972642324,
            "COE": 0,
            "NDA": 0.0149633399551969,
            "PMD": 2056.66453092821,
            "OZD": 262.907190702021,
            "SOE": 0,
            "GDP": 523970.0,
            "GDPPC": 477.068,
            "Population": 1098.31
        },
        "2003": {
            "CDA": 0.0370491660509373,
            "NOE": 0.023192239,
            "VOE": 0.033200529,
            "HAD": 4735.35814750008,
            "COE": 0.632983358,
            "NDA": 0.0116002450441799,
            "PMD": 2053.39312269147,
            "OZD": 266.904423476886,
            "SOE": 0.025326928,
            "GDP": 618358.0,
            "GDPPC": 553.382,
            "Population": 1117.42
        },
        "2004": {
            "CDA": 0.0341841208525806,
            "NOE": 0.024108413,
            "VOE": 0.034062907,
            "HAD": 4418.29603609602,
            "COE": 0.651811088,
            "NDA": 0.0105790646637303,
            "PMD": 2017.37307344098,
            "OZD": 249.423914759939,
            "SOE": 0.026559171,
            "GDP": 721589.0,
            "GDPPC": 635.054,
            "Population": 1136.27
        },
        "2005": {
            "CDA": 0.0335080009673872,
            "NOE": 0.025757864,
            "VOE": 0.032749304,
            "HAD": 4280.51308510245,
            "COE": 0.620063216,
            "NDA": 0.0114349863900456,
            "PMD": 2068.89430118092,
            "OZD": 255.304895879579,
            "SOE": 0.026968084,
            "GDP": 834217.0,
            "GDPPC": 722.492,
            "Population": 1154.64
        },
        "2006": {
            "CDA": 0.0364267337197863,
            "NOE": 0.027034897,
            "VOE": 0.034992661,
            "HAD": 4162.26947898475,
            "COE": 0.640685906,
            "NDA": 0.0142259721232323,
            "PMD": 2141.47542568091,
            "OZD": 265.651332783909,
            "SOE": 0.028447908,
            "GDP": 949117.0,
            "GDPPC": 809.568,
            "Population": 1172.37
        },
        "2007": {
            "CDA": 0.040590999340699,
            "NOE": 0.025983255,
            "VOE": 0.035914887,
            "HAD": 4021.77161982219,
            "COE": 0.652661679,
            "NDA": 0.0190228729536983,
            "PMD": 2217.35182558631,
            "OZD": 283.725702019337,
            "SOE": 0.029170253,
            "GDP": 1238700.0,
            "GDPPC": 1041.19,
            "Population": 1189.69
        },
        "2008": {
            "CDA": 0.0462532942941103,
            "NOE": 0.026920097,
            "VOE": 0.034303934,
            "HAD": 3872.2151677838,
            "COE": 0.686162417,
            "NDA": 0.0240135302982842,
            "PMD": 2295.26460342125,
            "OZD": 283.865895239492,
            "SOE": 0.030944737,
            "GDP": 1224100.0,
            "GDPPC": 1014.39,
            "Population": 1206.74
        },
        "2009": {
            "CDA": 0.0557513106636038,
            "NOE": 0.026040685,
            "VOE": 0.034027266,
            "HAD": 3610.26140374293,
            "COE": 0.657914703,
            "NDA": 0.0289610496989039,
            "PMD": 2302.26017283787,
            "OZD": 254.4057111292,
            "SOE": 0.031065259,
            "GDP": 1365370.0,
            "GDPPC": 1115.83,
            "Population": 1223.64
        },
        "2010": {
            "CDA": 0.0616565494868089,
            "NOE": 0.02664516,
            "VOE": 0.039054995,
            "HAD": 3402.36517444848,
            "COE": 0.675457873,
            "NDA": 0.0319097118723775,
            "PMD": 2345.83114360801,
            "OZD": 240.361597161129,
            "SOE": 0.031887795,
            "GDP": 1708460.0,
            "GDPPC": 1377.11,
            "Population": 1240.61
        },
        "2011": {
            "CDA": 0.0651439270615983,
            "NOE": 0.02809569,
            "VOE": 0.038492667,
            "HAD": 3214.69051471664,
            "COE": 0.701647843,
            "NDA": 0.0348358019378192,
            "PMD": 2454.84891268527,
            "OZD": 250.422656947237,
            "SOE": 0.033551037,
            "GDP": 1823050.0,
            "GDPPC": 1449.6,
            "Population": 1257.62
        },
        "2012": {
            "CDA": 0.0674672851568203,
            "NOE": 0.02797137,
            "VOE": 0.038874465,
            "HAD": 3011.61106345002,
            "COE": 0.674636955,
            "NDA": 0.0321085225777724,
            "PMD": 2595.46580053385,
            "OZD": 256.311418397578,
            "SOE": 0.033210441,
            "GDP": 1827640.0,
            "GDPPC": 1434.02,
            "Population": 1274.49
        },
        "2013": {
            "CDA": 0.0656154302263841,
            "NOE": 0.027744938,
            "VOE": 0.035801302,
            "HAD": 2796.62285145246,
            "COE": 0.680875654,
            "NDA": 0.0277872552337597,
            "PMD": 2739.6749995572,
            "OZD": 271.044750052454,
            "SOE": 0.033350765,
            "GDP": 1856720.0,
            "GDPPC": 1438.06,
            "Population": 1291.13
        },
        "2014": {
            "CDA": 0.0657247508994079,
            "NOE": 0.029587068,
            "VOE": 0.042531097,
            "HAD": 2556.75648948779,
            "COE": 0.700919354,
            "NDA": 0.0231830882234261,
            "PMD": 2791.11069934649,
            "OZD": 271.58028710556,
            "SOE": 0.034459214,
            "GDP": 2039130.0,
            "GDPPC": 1559.86,
            "Population": 1307.25
        },
        "2015": {
            "CDA": 0.0637748325315677,
            "NOE": 0.030617525,
            "VOE": 0.042637851,
            "HAD": 2401.85582831348,
            "COE": 0.728253346,
            "NDA": 0.0191077971567277,
            "PMD": 2808.19256579716,
            "OZD": 279.473927548262,
            "SOE": 0.035378175,
            "GDP": 2103590.0,
            "GDPPC": 1590.17,
            "Population": 1322.87
        },
        "2016": {
            "CDA": 0.0595299215764145,
            "NOE": 0.031780612,
            "VOE": 0.038664454,
            "HAD": 2231.75814157969,
            "COE": 0.752006656,
            "NDA": 0.0149397830614295,
            "PMD": 2712.3622185565,
            "OZD": 285.366234551629,
            "SOE": 0.036187864,
            "GDP": 2294800.0,
            "GDPPC": 1714.28,
            "Population": 1338.64
        },
        "2017": {
            "CDA": 0.0543594393795279,
            "NOE": 0.0325454,
            "VOE": 0.038249027,
            "HAD": 2099.50544228203,
            "COE": 0.731298566,
            "NDA": 0.0125982504777764,
            "PMD": 2640.19959440492,
            "OZD": 287.791899732754,
            "SOE": 0.035548736,
            "GDP": 2651470.0,
            "GDPPC": 1957.97,
            "Population": 1354.2
        },
        "2018": {
            "CDA": 0.0513617742543797,
            "NOE": 0.033789323,
            "VOE": 0.039731588,
            "HAD": 1986.73637562285,
            "COE": 0.758780144,
            "NDA": 0.0113373521635278,
            "PMD": 2667.98883124644,
            "OZD": 291.453202824523,
            "SOE": 0.03672373,
            "GDP": 2702930.0,
            "GDPPC": 1974.38,
            "Population": 1369.0
        }
    },
    "BRA": {
        "2000": {
            "CDA": 0.0508490034589015,
            "NOE": 0,
            "VOE": 0,
            "HAD": 855.628469355309,
            "COE": 0,
            "NDA": 0.0144056630122174,
            "PMD": 863.922570803297,
            "OZD": 18.5713470296028,
            "SOE": 0,
            "GDP": 655454.0,
            "GDPPC": 3772.05,
            "Population": 173.766
        },
        "2001": {
            "CDA": 0.0495260891822749,
            "NOE": 0,
            "VOE": 0,
            "HAD": 805.310565709065,
            "COE": 0,
            "NDA": 0.0171049222398767,
            "PMD": 847.625901387153,
            "OZD": 19.9626854934736,
            "SOE": 0,
            "GDP": 559982.0,
            "GDPPC": 3177.94,
            "Population": 176.209
        },
        "2002": {
            "CDA": 0.0426807033134782,
            "NOE": 0,
            "VOE": 0,
            "HAD": 754.689175314736,
            "COE": 0,
            "NDA": 0.0205919086342572,
            "PMD": 836.287337522405,
            "OZD": 20.8451385425653,
            "SOE": 0,
            "GDP": 509798.0,
            "GDPPC": 2856.03,
            "Population": 178.499
        },
        "2003": {
            "CDA": 0.0338818739105584,
            "NOE": 0.007927715,
            "VOE": 0.0560283,
            "HAD": 705.482324899023,
            "COE": 0.174864528,
            "NDA": 0.0248975801770386,
            "PMD": 829.243538379361,
            "OZD": 20.1883336839119,
            "SOE": 0.009107155,
            "GDP": 558232.0,
            "GDPPC": 3089.14,
            "Population": 180.708
        },
        "2004": {
            "CDA": 0.026238416088231,
            "NOE": 0.007772736,
            "VOE": 0.052895715,
            "HAD": 659.456170395409,
            "COE": 0.16898412,
            "NDA": 0.0317401361943601,
            "PMD": 821.771686585142,
            "OZD": 15.3992241539813,
            "SOE": 0.008525494,
            "GDP": 669290.0,
            "GDPPC": 3660.02,
            "Population": 182.865
        },
        "2005": {
            "CDA": 0.0197626854881086,
            "NOE": 0.00828081,
            "VOE": 0.052991117,
            "HAD": 609.708650793083,
            "COE": 0.171131627,
            "NDA": 0.036169693917548,
            "PMD": 795.590734507953,
            "OZD": 13.8592254777059,
            "SOE": 0.0081696,
            "GDP": 891633.0,
            "GDPPC": 4819.87,
            "Population": 184.991
        },
        "2006": {
            "CDA": 0.0155718994480918,
            "NOE": 0.008377018,
            "VOE": 0.048569493,
            "HAD": 566.39128126163,
            "COE": 0.164961128,
            "NDA": 0.0333007686999562,
            "PMD": 787.469025998654,
            "OZD": 15.3483782674589,
            "SOE": 0.007997036,
            "GDP": 1107630.0,
            "GDPPC": 5921.18,
            "Population": 187.062
        },
        "2007": {
            "CDA": 0.014715273060286,
            "NOE": 0.008361372,
            "VOE": 0.046497638,
            "HAD": 525.541735243076,
            "COE": 0.172053706,
            "NDA": 0.0333626026277256,
            "PMD": 777.479042865182,
            "OZD": 14.5945466524995,
            "SOE": 0.007679291,
            "GDP": 1397110.0,
            "GDPPC": 7390.65,
            "Population": 189.038
        },
        "2008": {
            "CDA": 0.0166850236927403,
            "NOE": 0.00808622,
            "VOE": 0.038591301,
            "HAD": 486.702340119221,
            "COE": 0.152215884,
            "NDA": 0.0300811199358335,
            "PMD": 768.654637165969,
            "OZD": 12.2787597211517,
            "SOE": 0.007253545,
            "GDP": 1695860.0,
            "GDPPC": 8878.36,
            "Population": 191.01
        },
        "2009": {
            "CDA": 0.013951052091294,
            "NOE": 0.00792394,
            "VOE": 0.040993891,
            "HAD": 449.96803402991,
            "COE": 0.145563948,
            "NDA": 0.0224101199962639,
            "PMD": 758.725637973234,
            "OZD": 11.5935478453927,
            "SOE": 0.006938581,
            "GDP": 1669200.0,
            "GDPPC": 8649.58,
            "Population": 192.981
        },
        "2010": {
            "CDA": 0.0201512473132477,
            "NOE": 0.007961348,
            "VOE": 0.045804094,
            "HAD": 415.555790879986,
            "COE": 0.16145948,
            "NDA": 0.0209214167096217,
            "PMD": 741.675520093616,
            "OZD": 13.3177972055252,
            "SOE": 0.006508412,
            "GDP": 2208700.0,
            "GDPPC": 11333.02,
            "Population": 194.891
        },
        "2011": {
            "CDA": 0.0265091052517268,
            "NOE": 0.007830092,
            "VOE": 0.042537564,
            "HAD": 384.996999056454,
            "COE": 0.146644324,
            "NDA": 0.0188724998871532,
            "PMD": 714.980505056718,
            "OZD": 17.1958508393725,
            "SOE": 0.00662714,
            "GDP": 2614030.0,
            "GDPPC": 13295.9,
            "Population": 196.604
        },
        "2012": {
            "CDA": 0.0326194782603157,
            "NOE": 0.007828321,
            "VOE": 0.045162511,
            "HAD": 351.385510201074,
            "COE": 0.149538904,
            "NDA": 0.0166518425629625,
            "PMD": 669.924738795375,
            "OZD": 18.6111532295926,
            "SOE": 0.006541006,
            "GDP": 2464050.0,
            "GDPPC": 12424.95,
            "Population": 198.315
        },
        "2013": {
            "CDA": 0.0384757284204782,
            "NOE": 0.007693199,
            "VOE": 0.043966483,
            "HAD": 320.312995592255,
            "COE": 0.139373945,
            "NDA": 0.0148718142386197,
            "PMD": 629.238405312467,
            "OZD": 19.599706058355,
            "SOE": 0.006308724,
            "GDP": 2471720.0,
            "GDPPC": 12358.34,
            "Population": 200.004
        },
        "2014": {
            "CDA": 0.0453185921824459,
            "NOE": 0.007974082,
            "VOE": 0.046354768,
            "HAD": 290.976260574411,
            "COE": 0.147607983,
            "NDA": 0.0170261346325025,
            "PMD": 590.066304857164,
            "OZD": 19.2468079981651,
            "SOE": 0.006282533,
            "GDP": 2456060.0,
            "GDPPC": 12175.68,
            "Population": 201.718
        },
        "2015": {
            "CDA": 0.0454451430571707,
            "NOE": 0.008221183,
            "VOE": 0.049524491,
            "HAD": 267.64838853395,
            "COE": 0.158031449,
            "NDA": 0.0164265557975922,
            "PMD": 568.750678460163,
            "OZD": 18.8584330715035,
            "SOE": 0.006384705,
            "GDP": 1800050.0,
            "GDPPC": 8846.48,
            "Population": 203.476
        },
        "2016": {
            "CDA": 0.039429296902924,
            "NOE": 0.007879375,
            "VOE": 0.053293453,
            "HAD": 248.086821905998,
            "COE": 0.151492237,
            "NDA": 0.0142448396356178,
            "PMD": 568.007193223927,
            "OZD": 20.5141793184444,
            "SOE": 0.006094274,
            "GDP": 1796620.0,
            "GDPPC": 8757.3,
            "Population": 205.157
        },
        "2017": {
            "CDA": 0.033070778486274,
            "NOE": 0.007966622,
            "VOE": 0.050885688,
            "HAD": 227.974371462771,
            "COE": 0.150314201,
            "NDA": 0.0176570809881151,
            "PMD": 552.845585345462,
            "OZD": 18.5739125718665,
            "SOE": 0.005964575,
            "GDP": 2063520.0,
            "GDPPC": 9978.09,
            "Population": 206.805
        },
        "2018": {
            "CDA": 0.025264466596481,
            "NOE": 0.008101107,
            "VOE": 0.049671047,
            "HAD": 211.981653557828,
            "COE": 0.14740961,
            "NDA": 0.0152904841691575,
            "PMD": 546.055470190209,
            "OZD": 25.1508129811731,
            "SOE": 0.00600372,
            "GDP": 1916930.0,
            "GDPPC": 9194.15,
            "Population": 208.495
        }
    },
    "DEU": {
        "2000": {
            "CDA": -0.0216615591723935,
            "NOE": 0,
            "VOE": 0,
            "HAD": 1.14953320977876,
            "COE": 0,
            "NDA": -0.0768934832370225,
            "PMD": 649.694532774264,
            "OZD": 16.3181819072254,
            "SOE": 0,
            "GDP": 1948840.0,
            "GDPPC": 23924.88,
            "Population": 81.457
        },
        "2001": {
            "CDA": -0.0124658785504077,
            "NOE": 0,
            "VOE": 0,
            "HAD": 1.08237342687651,
            "COE": 0,
            "NDA": -0.0930209550988399,
            "PMD": 616.416177616548,
            "OZD": 15.193951329858,
            "SOE": 0,
            "GDP": 1945800.0,
            "GDPPC": 23869.77,
            "Population": 81.518
        },
        "2002": {
            "CDA": -0.0110319787819451,
            "NOE": 0,
            "VOE": 0,
            "HAD": 1.02645224061181,
            "COE": 0,
            "NDA": -0.102983007259749,
            "PMD": 592.538019337306,
            "OZD": 20.1159015210953,
            "SOE": 0,
            "GDP": 2077020.0,
            "GDPPC": 25460.33,
            "Population": 81.579
        },
        "2003": {
            "CDA": -0.0106828245620729,
            "NOE": 0.034738649,
            "VOE": 0.00728765,
            "HAD": 0.967360966252686,
            "COE": 0.254125896,
            "NDA": -0.111904663247403,
            "PMD": 569.972427404411,
            "OZD": 20.3489236849764,
            "SOE": 0.009951276,
            "GDP": 2501010.0,
            "GDPPC": 30668.85,
            "Population": 81.549
        },
        "2004": {
            "CDA": -0.0117664926482646,
            "NOE": 0.0304434,
            "VOE": 0.005740108,
            "HAD": 0.888388293987482,
            "COE": 0.224802776,
            "NDA": -0.0997990307125855,
            "PMD": 536.904090203603,
            "OZD": 19.7748382376876,
            "SOE": 0.008716473,
            "GDP": 2813080.0,
            "GDPPC": 34534.81,
            "Population": 81.456
        },
        "2005": {
            "CDA": -0.0141975224951905,
            "NOE": 0.030164021,
            "VOE": 0.006284151,
            "HAD": 0.825559994275232,
            "COE": 0.223699885,
            "NDA": -0.0843128152628441,
            "PMD": 517.193767465448,
            "OZD": 17.0952389088559,
            "SOE": 0.008328421,
            "GDP": 2848440.0,
            "GDPPC": 35020.2,
            "Population": 81.337
        },
        "2006": {
            "CDA": -0.0096978265654542,
            "NOE": 0.029078172,
            "VOE": 0.005144385,
            "HAD": 0.766560430064483,
            "COE": 0.217815211,
            "NDA": -0.0585110804245215,
            "PMD": 506.542949651055,
            "OZD": 16.8507649324784,
            "SOE": 0.007454346,
            "GDP": 2994860.0,
            "GDPPC": 36894.47,
            "Population": 81.174
        },
        "2007": {
            "CDA": -0.0113563953831979,
            "NOE": 0.02674193,
            "VOE": 0.004635682,
            "HAD": 0.712309904816512,
            "COE": 0.2014408,
            "NDA": -0.0248840234857082,
            "PMD": 505.781160784683,
            "OZD": 17.4942642486715,
            "SOE": 0.006573334,
            "GDP": 3425980.0,
            "GDPPC": 42299.86,
            "Population": 80.993
        },
        "2008": {
            "CDA": -0.0127236128815203,
            "NOE": 0.026055314,
            "VOE": 0.005779364,
            "HAD": 0.66102177618708,
            "COE": 0.195714118,
            "NDA": -0.0244053667189604,
            "PMD": 507.614123898401,
            "OZD": 16.079734625542,
            "SOE": 0.006113259,
            "GDP": 3744850.0,
            "GDPPC": 46367.86,
            "Population": 80.764
        },
        "2009": {
            "CDA": -0.0245241391430412,
            "NOE": 0.026301717,
            "VOE": 0.006473035,
            "HAD": 0.617942174738661,
            "COE": 0.191103922,
            "NDA": -0.0234950167822,
            "PMD": 509.912458043668,
            "OZD": 16.8086484407387,
            "SOE": 0.005565414,
            "GDP": 3407560.0,
            "GDPPC": 42338.71,
            "Population": 80.483
        },
        "2010": {
            "CDA": -0.0250113905436309,
            "NOE": 0.025928675,
            "VOE": 0.005932953,
            "HAD": 0.581036863935556,
            "COE": 0.195432842,
            "NDA": -0.0200952331918006,
            "PMD": 503.825592816902,
            "OZD": 16.4906696164571,
            "SOE": 0.004964762,
            "GDP": 3402440.0,
            "GDPPC": 42379.71,
            "Population": 80.285
        },
        "2011": {
            "CDA": -0.024593641317491,
            "NOE": 0.026245698,
            "VOE": 0.00570379,
            "HAD": 0.554049960666731,
            "COE": 0.188129526,
            "NDA": -0.0216033394818449,
            "PMD": 485.714578578794,
            "OZD": 16.6185068368835,
            "SOE": 0.004659005,
            "GDP": 3748660.0,
            "GDPPC": 46697.38,
            "Population": 80.276
        },
        "2012": {
            "CDA": -0.0229367804784994,
            "NOE": 0.023361341,
            "VOE": 0.005486444,
            "HAD": 0.531271196192122,
            "COE": 0.179962206,
            "NDA": -0.0208572698156125,
            "PMD": 456.970801237672,
            "OZD": 16.8125106702504,
            "SOE": 0.004251805,
            "GDP": 3529380.0,
            "GDPPC": 43883.39,
            "Population": 80.426
        },
        "2013": {
            "CDA": -0.0172303749766998,
            "NOE": 0.022377319,
            "VOE": 0.005298123,
            "HAD": 0.517735604529322,
            "COE": 0.176065841,
            "NDA": -0.0172298735221728,
            "PMD": 428.908121043978,
            "OZD": 17.3417796811598,
            "SOE": 0.00393075,
            "GDP": 3733860.0,
            "GDPPC": 46299.37,
            "Population": 80.646
        },
        "2014": {
            "CDA": -0.0156579102028703,
            "NOE": 0.022933052,
            "VOE": 0.005384502,
            "HAD": 0.49547429021199,
            "COE": 0.178595381,
            "NDA": -0.0084787117501231,
            "PMD": 392.996333496656,
            "OZD": 18.9420998246312,
            "SOE": 0.00388728,
            "GDP": 3890100.0,
            "GDPPC": 48035.8,
            "Population": 80.983
        },
        "2015": {
            "CDA": -0.0133647080163295,
            "NOE": 0.021544323,
            "VOE": 0.005736259,
            "HAD": 0.485357216384184,
            "COE": 0.173439511,
            "NDA": -0.0038648353456125,
            "PMD": 375.48551576862,
            "OZD": 19.7561425069767,
            "SOE": 0.003459393,
            "GDP": 3357930.0,
            "GDPPC": 41107.22,
            "Population": 81.687
        },
        "2016": {
            "CDA": -0.0084516422073964,
            "NOE": 0.02168108,
            "VOE": 0.005496381,
            "HAD": 0.464113930840386,
            "COE": 0.168054481,
            "NDA": -0.0030422545327419,
            "PMD": 353.720544396964,
            "OZD": 19.2992804929681,
            "SOE": 0.003200491,
            "GDP": 3468900.0,
            "GDPPC": 42124.2,
            "Population": 82.349
        },
        "2017": {
            "CDA": -0.0061363256942705,
            "NOE": 0.020335523,
            "VOE": 0.00518496,
            "HAD": 0.439922855395074,
            "COE": 0.165644612,
            "NDA": -0.003186987711114,
            "PMD": 338.279057448235,
            "OZD": 16.9698182015674,
            "SOE": 0.002977666,
            "GDP": 3689550.0,
            "GDPPC": 44636.83,
            "Population": 82.657
        },
        "2018": {
            "CDA": -0.0060097156622678,
            "NOE": 0.019245106,
            "VOE": 0.005362096,
            "HAD": 0.42102138725415,
            "COE": 0.158383266,
            "NDA": -0.0085926999679611,
            "PMD": 335.387659756336,
            "OZD": 17.7510705747974,
            "SOE": 0.002905382,
            "GDP": 3976250.0,
            "GDPPC": 47961.04,
            "Population": 82.906
        }
    },
    "CHN": {
        "2000": {
            "CDA": 0.0319163145151085,
            "NOE": 0,
            "VOE": 0,
            "HAD": 2664.04818641516,
            "COE": 0,
            "NDA": 0.0261062998008492,
            "PMD": 2067.86795022848,
            "OZD": 245.438247212346,
            "SOE": 0,
            "GDP": 1205530.0,
            "GDPPC": 951.163,
            "Population": 1267.43
        },
        "2001": {
            "CDA": 0.0250754955394503,
            "NOE": 0,
            "VOE": 0,
            "HAD": 2468.66434762073,
            "COE": 0,
            "NDA": 0.0221647910789442,
            "PMD": 2061.75906732253,
            "OZD": 238.758207202591,
            "SOE": 0,
            "GDP": 1333650.0,
            "GDPPC": 1044.96,
            "Population": 1276.27
        },
        "2002": {
            "CDA": 0.0226059626261441,
            "NOE": 0,
            "VOE": 0,
            "HAD": 2305.3259814855,
            "COE": 0,
            "NDA": 0.0190614927519654,
            "PMD": 2067.45082233847,
            "OZD": 228.448965121856,
            "SOE": 0,
            "GDP": 1465830.0,
            "GDPPC": 1141.14,
            "Population": 1284.53
        },
        "2003": {
            "CDA": 0.0291144328845057,
            "NOE": 0.043599382,
            "VOE": 0.024190316,
            "HAD": 2144.15961946567,
            "COE": 0.647950047,
            "NDA": 0.0129102759355715,
            "PMD": 2062.3727323158,
            "OZD": 229.348631999883,
            "SOE": 0.07009387,
            "GDP": 1656960.0,
            "GDPPC": 1282.21,
            "Population": 1292.27
        },
        "2004": {
            "CDA": 0.0421242547745735,
            "NOE": 0.045757617,
            "VOE": 0.023529211,
            "HAD": 2007.79275458494,
            "COE": 0.64248173,
            "NDA": 0.0090229541241584,
            "PMD": 2075.52469064756,
            "OZD": 234.879987027113,
            "SOE": 0.07670669,
            "GDP": 1949450.0,
            "GDPPC": 1499.71,
            "Population": 1299.88
        },
        "2005": {
            "CDA": 0.0606591296222543,
            "NOE": 0.048853196,
            "VOE": 0.023842854,
            "HAD": 1837.90369780285,
            "COE": 0.639748973,
            "NDA": 0.013200272248524,
            "PMD": 2048.98896770878,
            "OZD": 225.422809027024,
            "SOE": 0.081456068,
            "GDP": 2290020.0,
            "GDPPC": 1751.37,
            "Population": 1307.56
        },
        "2006": {
            "CDA": 0.0810055661771325,
            "NOE": 0.05270309,
            "VOE": 0.025133893,
            "HAD": 1632.27348940385,
            "COE": 0.671730746,
            "NDA": 0.0200958930236774,
            "PMD": 1984.0739620869,
            "OZD": 223.925406520652,
            "SOE": 0.081440992,
            "GDP": 2754150.0,
            "GDPPC": 2095.24,
            "Population": 1314.48
        },
        "2007": {
            "CDA": 0.0984757840605412,
            "NOE": 0.057331128,
            "VOE": 0.024555324,
            "HAD": 1454.25900838581,
            "COE": 0.696505535,
            "NDA": 0.0216624633990559,
            "PMD": 1964.41932006265,
            "OZD": 215.39216765738,
            "SOE": 0.081699019,
            "GDP": 3555660.0,
            "GDPPC": 2691.05,
            "Population": 1321.29
        },
        "2008": {
            "CDA": 0.107520151889489,
            "NOE": 0.058485866,
            "VOE": 0.023820342,
            "HAD": 1313.39361894223,
            "COE": 0.687930987,
            "NDA": 0.0229878986500955,
            "PMD": 1984.61346919553,
            "OZD": 214.874230831398,
            "SOE": 0.079704984,
            "GDP": 4577280.0,
            "GDPPC": 3446.7,
            "Population": 1328.02
        },
        "2009": {
            "CDA": 0.108696916536696,
            "NOE": 0.061222794,
            "VOE": 0.0235721,
            "HAD": 1190.45813228385,
            "COE": 0.69568642,
            "NDA": 0.0211238076048743,
            "PMD": 2011.24830502701,
            "OZD": 191.524902078403,
            "SOE": 0.077517551,
            "GDP": 5088990.0,
            "GDPPC": 3813.41,
            "Population": 1334.5
        },
        "2010": {
            "CDA": 0.106039864286714,
            "NOE": 0.062398604,
            "VOE": 0.023295503,
            "HAD": 1086.90511993148,
            "COE": 0.673202036,
            "NDA": 0.0171182391908333,
            "PMD": 2029.53420916107,
            "OZD": 178.175605819647,
            "SOE": 0.074403099,
            "GDP": 6033830.0,
            "GDPPC": 4499.8,
            "Population": 1340.91
        },
        "2011": {
            "CDA": 0.0985814343885516,
            "NOE": 0.065460997,
            "VOE": 0.024878258,
            "HAD": 988.566509291698,
            "COE": 0.689852495,
            "NDA": 0.0120496114977826,
            "PMD": 2024.86049496763,
            "OZD": 156.417911237475,
            "SOE": 0.07701806,
            "GDP": 7492210.0,
            "GDPPC": 5553.24,
            "Population": 1349.16
        },
        "2012": {
            "CDA": 0.0865662694738314,
            "NOE": 0.064814979,
            "VOE": 0.024332179,
            "HAD": 891.056508950006,
            "COE": 0.684705021,
            "NDA": 0.0087100867644081,
            "PMD": 2004.99974841213,
            "OZD": 131.599471189643,
            "SOE": 0.076556443,
            "GDP": 8539580.0,
            "GDPPC": 6282.71,
            "Population": 1359.22
        },
        "2013": {
            "CDA": 0.0754960550776005,
            "NOE": 0.068144389,
            "VOE": 0.024772547,
            "HAD": 807.905177877506,
            "COE": 0.703810497,
            "NDA": 0.0054669445738664,
            "PMD": 1987.06097141272,
            "OZD": 108.138573525991,
            "SOE": 0.078041733,
            "GDP": 9624930.0,
            "GDPPC": 7039.57,
            "Population": 1367.26
        },
        "2014": {
            "CDA": 0.0647305765649877,
            "NOE": 0.069344712,
            "VOE": 0.025299173,
            "HAD": 739.096614765329,
            "COE": 0.703644534,
            "NDA": 0.0034746251474637,
            "PMD": 1962.45897411453,
            "OZD": 94.589640302773,
            "SOE": 0.078936586,
            "GDP": 10524240.0,
            "GDPPC": 7645.88,
            "Population": 1376.46
        },
        "2015": {
            "CDA": 0.0532829661711951,
            "NOE": 0.069539688,
            "VOE": 0.024778849,
            "HAD": 678.316882499448,
            "COE": 0.704168181,
            "NDA": 0.0030219839192515,
            "PMD": 1921.88594564167,
            "OZD": 94.7304272789653,
            "SOE": 0.079088153,
            "GDP": 11113510.0,
            "GDPPC": 8034.29,
            "Population": 1383.26
        },
        "2016": {
            "CDA": 0.0419195270164825,
            "NOE": 0.069725193,
            "VOE": 0.024716981,
            "HAD": 631.780518206887,
            "COE": 0.68897673,
            "NDA": 0.0036004135362088,
            "PMD": 1854.62845969708,
            "OZD": 102.184919621425,
            "SOE": 0.078784265,
            "GDP": 11226900.0,
            "GDPPC": 8063.45,
            "Population": 1392.32
        },
        "2017": {
            "CDA": 0.0316137040348845,
            "NOE": 0.071488309,
            "VOE": 0.025139657,
            "HAD": 586.744172883419,
            "COE": 0.689349448,
            "NDA": 0.0039646012445404,
            "PMD": 1782.88874922942,
            "OZD": 102.670967262718,
            "SOE": 0.079073764,
            "GDP": 12265330.0,
            "GDPPC": 8760.26,
            "Population": 1400.11
        },
        "2018": {
            "CDA": 0.0225597136176496,
            "NOE": 0.071157408,
            "VOE": 0.024035824,
            "HAD": 532.528221310033,
            "COE": 0.693456622,
            "NDA": 0.0047461758485527,
            "PMD": 1749.996403638,
            "OZD": 81.2555610368657,
            "SOE": 0.078259105,
            "GDP": 13841810.0,
            "GDPPC": 9848.95,
            "Population": 1405.41
        }
    },
    "ZAF": {
        "2000": {
            "CDA": 0.0253840570906154,
            "NOE": 0,
            "VOE": 0,
            "HAD": 1829.51012730892,
            "COE": 0,
            "NDA": 0.0137857313131968,
            "PMD": 2294.18291681784,
            "OZD": 22.0044985971708,
            "SOE": 0,
            "GDP": 151855.0,
            "GDPPC": 3382.07,
            "Population": 44.9
        },
        "2001": {
            "CDA": 0.0238603197402407,
            "NOE": 0,
            "VOE": 0,
            "HAD": 1749.87886011282,
            "COE": 0,
            "NDA": 0.0050912845807127,
            "PMD": 2266.63325974121,
            "OZD": 20.3633058484335,
            "SOE": 0,
            "GDP": 135527.0,
            "GDPPC": 2964.03,
            "Population": 45.724
        },
        "2002": {
            "CDA": 0.0143340642232992,
            "NOE": 0,
            "VOE": 0,
            "HAD": 1708.11352607286,
            "COE": 0,
            "NDA": 0.0043184274022727,
            "PMD": 2279.46375939749,
            "OZD": 16.5887256256027,
            "SOE": 0,
            "GDP": 129384.99999999999,
            "GDPPC": 2791.18,
            "Population": 46.355
        },
        "2003": {
            "CDA": 0.0115445737804012,
            "NOE": 0.024783969,
            "VOE": 0.041791729,
            "HAD": 1662.00986148155,
            "COE": 0.279038421,
            "NDA": 0.0006563231093514,
            "PMD": 2298.29024373628,
            "OZD": 18.0704296848805,
            "SOE": 0.039784863,
            "GDP": 197017.0,
            "GDPPC": 4209.22,
            "Population": 46.806
        },
        "2004": {
            "CDA": 0.0146196100239342,
            "NOE": 0.02523431,
            "VOE": 0.034970163,
            "HAD": 1580.66420084166,
            "COE": 0.296263455,
            "NDA": -0.0042927325199694,
            "PMD": 2277.34810920854,
            "OZD": 26.7690285933854,
            "SOE": 0.041742134,
            "GDP": 256188.0,
            "GDPPC": 5415.09,
            "Population": 47.31
        },
        "2005": {
            "CDA": 0.0165400617451177,
            "NOE": 0.026237713,
            "VOE": 0.03374737,
            "HAD": 1502.07926362301,
            "COE": 0.325187276,
            "NDA": -0.0120795223115143,
            "PMD": 2269.91666140899,
            "OZD": 35.2930996091175,
            "SOE": 0.042359406,
            "GDP": 288749.0,
            "GDPPC": 6033.21,
            "Population": 47.86
        },
        "2006": {
            "CDA": 0.0204671839199391,
            "NOE": 0.027626576,
            "VOE": 0.03088338,
            "HAD": 1426.89677006448,
            "COE": 0.332928989,
            "NDA": -0.0137212625689612,
            "PMD": 2302.44589732383,
            "OZD": 45.4380010603597,
            "SOE": 0.043157556,
            "GDP": 304055.0,
            "GDPPC": 6276.17,
            "Population": 48.446
        },
        "2007": {
            "CDA": 0.0270591297694467,
            "NOE": 0.028150783,
            "VOE": 0.031032994,
            "HAD": 1279.84545187563,
            "COE": 0.351590166,
            "NDA": -0.0089569385254166,
            "PMD": 2309.0046464547,
            "OZD": 37.6034078739369,
            "SOE": 0.042799387,
            "GDP": 332650.0,
            "GDPPC": 6776.47,
            "Population": 49.089
        },
        "2008": {
            "CDA": 0.0323369742948052,
            "NOE": 0.029723088,
            "VOE": 0.031890087,
            "HAD": 1145.97195415386,
            "COE": 0.363668505,
            "NDA": -0.0067873486913758,
            "PMD": 2340.12197603997,
            "OZD": 30.8489485516923,
            "SOE": 0.044796397,
            "GDP": 316491.0,
            "GDPPC": 6355.88,
            "Population": 49.795
        },
        "2009": {
            "CDA": 0.0339727894383781,
            "NOE": 0.030076989,
            "VOE": 0.027054138,
            "HAD": 1013.33191115229,
            "COE": 0.368077764,
            "NDA": -0.0064234208359542,
            "PMD": 2332.51325460956,
            "OZD": 23.8246455619146,
            "SOE": 0.044631902,
            "GDP": 331184.0,
            "GDPPC": 6552.27,
            "Population": 50.545
        },
        "2010": {
            "CDA": 0.0318579615162593,
            "NOE": 0.030412189,
            "VOE": 0.035548236,
            "HAD": 891.558027797533,
            "COE": 0.387827647,
            "NDA": -0.0108257319320733,
            "PMD": 2288.62633454097,
            "OZD": 21.7862994450804,
            "SOE": 0.044710592,
            "GDP": 417315.0,
            "GDPPC": 8130.19,
            "Population": 51.329
        },
        "2011": {
            "CDA": 0.0235588794574475,
            "NOE": 0.031088337,
            "VOE": 0.036488759,
            "HAD": 783.274517773292,
            "COE": 0.39087009,
            "NDA": -0.0157272064014233,
            "PMD": 2210.39595605266,
            "OZD": 25.1114962355699,
            "SOE": 0.045554087,
            "GDP": 458708.0,
            "GDPPC": 8799.48,
            "Population": 52.129
        },
        "2012": {
            "CDA": 0.0095157754692769,
            "NOE": 0.031132651,
            "VOE": 0.035003865,
            "HAD": 703.311460339872,
            "COE": 0.394751947,
            "NDA": -0.0082311962872088,
            "PMD": 2149.90469145774,
            "OZD": 28.7869729083587,
            "SOE": 0.044966032,
            "GDP": 434400.0,
            "GDPPC": 8207.06,
            "Population": 52.93
        },
        "2013": {
            "CDA": 0.0002132571830073,
            "NOE": 0.032208524,
            "VOE": 0.032284413,
            "HAD": 635.442121955087,
            "COE": 0.415675952,
            "NDA": -0.0066373609831259,
            "PMD": 2104.6328426683,
            "OZD": 33.2385813087448,
            "SOE": 0.046271628,
            "GDP": 400877.0,
            "GDPPC": 7458.04,
            "Population": 53.751
        },
        "2014": {
            "CDA": -0.0010025346262198,
            "NOE": 0.032621817,
            "VOE": 0.033951409,
            "HAD": 591.844162654478,
            "COE": 0.425414424,
            "NDA": -0.0024220233579569,
            "PMD": 2104.88464518522,
            "OZD": 26.9865899609217,
            "SOE": 0.046723906,
            "GDP": 381195.0,
            "GDPPC": 6984.93,
            "Population": 54.574
        },
        "2015": {
            "CDA": -0.0139994942136521,
            "NOE": 0.034543178,
            "VOE": 0.041520325,
            "HAD": 534.011905884285,
            "COE": 0.458283787,
            "NDA": -0.0028956864228477,
            "PMD": 2085.08616176755,
            "OZD": 24.0356619380362,
            "SOE": 0.048096916,
            "GDP": 346663.0,
            "GDPPC": 6256.67,
            "Population": 55.407
        },
        "2016": {
            "CDA": -0.0204808747627885,
            "NOE": 0.034533059,
            "VOE": 0.039442449,
            "HAD": 475.465804321871,
            "COE": 0.458808587,
            "NDA": -0.0098804404970478,
            "PMD": 2023.23233030162,
            "OZD": 25.6538347747405,
            "SOE": 0.048289437,
            "GDP": 323493.0,
            "GDPPC": 5750.79,
            "Population": 56.252
        },
        "2017": {
            "CDA": -0.0184335176974824,
            "NOE": 0.034560267,
            "VOE": 0.034920884,
            "HAD": 429.094015645664,
            "COE": 0.471064617,
            "NDA": -0.0067685030066113,
            "PMD": 1964.62823668347,
            "OZD": 28.3277030513035,
            "SOE": 0.047200588,
            "GDP": 381317.0,
            "GDPPC": 6678.29,
            "Population": 57.098
        },
        "2018": {
            "CDA": -0.0143585264774246,
            "NOE": 0.035251003,
            "VOE": 0.03555365,
            "HAD": 379.740408166072,
            "COE": 0.4880206,
            "NDA": -0.0083006280029561,
            "PMD": 1847.56806572279,
            "OZD": 27.7503286550752,
            "SOE": 0.047695534,
            "GDP": 403991.0,
            "GDPPC": 6972.7,
            "Population": 57.939
        }
    },
    "AUS": {
        "2000": {
            "CDA": 0.0260037795330414,
            "NOE": 0,
            "VOE": 0,
            "HAD": 5.87091063927944,
            "COE": 0,
            "NDA": 0.0173631517473287,
            "PMD": 196.828712751718,
            "OZD": 3.0249160219659,
            "SOE": 0,
            "GDP": 399960.0,
            "GDPPC": 20895.4,
            "Population": 19.141
        },
        "2001": {
            "CDA": 0.0240469689998386,
            "NOE": 0,
            "VOE": 0,
            "HAD": 5.14328123512935,
            "COE": 0,
            "NDA": 0.0352257124372795,
            "PMD": 187.19072851246,
            "OZD": 3.93394416401251,
            "SOE": 0,
            "GDP": 377780.0,
            "GDPPC": 19486.8,
            "Population": 19.386
        },
        "2002": {
            "CDA": 0.0237461647711761,
            "NOE": 0,
            "VOE": 0,
            "HAD": 4.49749917881868,
            "COE": 0,
            "NDA": 0.0444543151366676,
            "PMD": 177.823261823516,
            "OZD": 3.78504746083834,
            "SOE": 0,
            "GDP": 425288.0,
            "GDPPC": 21692.33,
            "Population": 19.605
        },
        "2003": {
            "CDA": 0.0221404063442743,
            "NOE": 0.023517682,
            "VOE": 0.031334417,
            "HAD": 3.89197118196266,
            "COE": 0.11700859,
            "NDA": 0.0224648175628477,
            "PMD": 167.381942170189,
            "OZD": 3.55530561074036,
            "SOE": 0.017093044,
            "GDP": 541063.0,
            "GDPPC": 27288.99,
            "Population": 19.827
        },
        "2004": {
            "CDA": 0.0189667033297702,
            "NOE": 0.022802188,
            "VOE": 0.047049325,
            "HAD": 3.36436900554985,
            "COE": 0.108941706,
            "NDA": 0.0206704244712643,
            "PMD": 156.913898630825,
            "OZD": 2.49070014128538,
            "SOE": 0.016509948,
            "GDP": 658572.0,
            "GDPPC": 32853.01,
            "Population": 20.046
        },
        "2005": {
            "CDA": 0.0152848447211527,
            "NOE": 0.024557517,
            "VOE": 0.054358498,
            "HAD": 2.95714434420067,
            "COE": 0.108451698,
            "NDA": 0.0009467734537473,
            "PMD": 148.837190797975,
            "OZD": 2.54712857980401,
            "SOE": 0.016572089,
            "GDP": 735940.0,
            "GDPPC": 36232.61,
            "Population": 20.312
        },
        "2006": {
            "CDA": 0.0158586189159275,
            "NOE": 0.023460901,
            "VOE": 0.054042458,
            "HAD": 2.62233589963042,
            "COE": 0.110413059,
            "NDA": -0.007945217280065,
            "PMD": 141.956154444636,
            "OZD": 2.6819233400742,
            "SOE": 0.015575422,
            "GDP": 782797.0,
            "GDPPC": 37949.1,
            "Population": 20.628
        },
        "2007": {
            "CDA": 0.0161999090351648,
            "NOE": 0.0220112,
            "VOE": 0.034739868,
            "HAD": 2.35119976166028,
            "COE": 0.101724241,
            "NDA": -0.0281771960793437,
            "PMD": 137.406436779101,
            "OZD": 2.61513797602171,
            "SOE": 0.014560302,
            "GDP": 949526.0,
            "GDPPC": 45180.86,
            "Population": 21.016
        },
        "2008": {
            "CDA": 0.0184669807479299,
            "NOE": 0.020938037,
            "VOE": 0.033910031,
            "HAD": 2.12176575759016,
            "COE": 0.091061774,
            "NDA": -0.0733729217476479,
            "PMD": 133.654612916538,
            "OZD": 2.41995466554505,
            "SOE": 0.013934555,
            "GDP": 1056490.0,
            "GDPPC": 49194.71,
            "Population": 21.476
        },
        "2009": {
            "CDA": 0.0210915765910435,
            "NOE": 0.02186474,
            "VOE": 0.045183567,
            "HAD": 1.92019500910366,
            "COE": 0.094740489,
            "NDA": -0.0776916538615851,
            "PMD": 129.672391942714,
            "OZD": 1.92273172504011,
            "SOE": 0.013360065,
            "GDP": 1000800.0,
            "GDPPC": 45770.5,
            "Population": 21.866
        },
        "2010": {
            "CDA": 0.0220546035736968,
            "NOE": 0.021068602,
            "VOE": 0.039459424,
            "HAD": 1.74671377265224,
            "COE": 0.090586083,
            "NDA": -0.0863795124737709,
            "PMD": 125.807466345162,
            "OZD": 1.80043509396114,
            "SOE": 0.012901608,
            "GDP": 1254500.0,
            "GDPPC": 56579.03,
            "Population": 22.172
        },
        "2011": {
            "CDA": 0.0199259047274005,
            "NOE": 0.019996158,
            "VOE": 0.041589714,
            "HAD": 1.60171325546845,
            "COE": 0.089091753,
            "NDA": -0.0098299155821417,
            "PMD": 122.344051351853,
            "OZD": 1.79200263692985,
            "SOE": 0.012012038,
            "GDP": 1515080.0,
            "GDPPC": 67270.36,
            "Population": 22.522
        },
        "2012": {
            "CDA": 0.0180433423355204,
            "NOE": 0.018966192,
            "VOE": 0.038959319,
            "HAD": 1.46734386195487,
            "COE": 0.087180019,
            "NDA": 0.0318347640800003,
            "PMD": 118.272103918927,
            "OZD": 2.29443463774775,
            "SOE": 0.011573199,
            "GDP": 1569430.0,
            "GDPPC": 68450.31,
            "Population": 22.928
        },
        "2013": {
            "CDA": 0.0119109375205497,
            "NOE": 0.019687114,
            "VOE": 0.042619416,
            "HAD": 1.37791876831026,
            "COE": 0.092699799,
            "NDA": 0.0118545703976842,
            "PMD": 117.009384552023,
            "OZD": 2.68980114838621,
            "SOE": 0.011080724,
            "GDP": 1519020.0,
            "GDPPC": 65200.37,
            "Population": 23.298
        },
        "2014": {
            "CDA": 0.0044400668316197,
            "NOE": 0.018989288,
            "VOE": 0.044572834,
            "HAD": 1.29773534357705,
            "COE": 0.088096139,
            "NDA": 0.0222128867118594,
            "PMD": 116.309245930396,
            "OZD": 2.77968721406063,
            "SOE": 0.010781767,
            "GDP": 1456600.0,
            "GDPPC": 61615.05,
            "Population": 23.64
        },
        "2015": {
            "CDA": -0.0023479351766282,
            "NOE": 0.019268181,
            "VOE": 0.046889566,
            "HAD": 1.21964377056837,
            "COE": 0.08797462,
            "NDA": 0.010754779187049,
            "PMD": 115.514467721313,
            "OZD": 2.80674022811047,
            "SOE": 0.010333113,
            "GDP": 1233100.0,
            "GDPPC": 51412.25,
            "Population": 23.985
        },
        "2016": {
            "CDA": -0.0088285505451804,
            "NOE": 0.0175858,
            "VOE": 0.041897972,
            "HAD": 1.11564296491599,
            "COE": 0.087640756,
            "NDA": 0.0040536969915574,
            "PMD": 109.48412907085,
            "OZD": 3.06257378737042,
            "SOE": 0.009342279,
            "GDP": 1263520.0,
            "GDPPC": 51813.64,
            "Population": 24.386
        },
        "2017": {
            "CDA": -0.0151562603157916,
            "NOE": 0.015100106,
            "VOE": 0.040292146,
            "HAD": 1.04246886550561,
            "COE": 0.0838975,
            "NDA": 0.0131158444293764,
            "PMD": 105.905385487475,
            "OZD": 2.14430687732376,
            "SOE": 0.00872793,
            "GDP": 1381620.0,
            "GDPPC": 55797.38,
            "Population": 24.761
        },
        "2018": {
            "CDA": -0.0176594976568314,
            "NOE": 0.014269762,
            "VOE": 0.039118086,
            "HAD": 0.992187586194753,
            "COE": 0.082529674,
            "NDA": 0.0055623844669172,
            "PMD": 106.366192399702,
            "OZD": 3.3975473036836,
            "SOE": 0.008080565,
            "GDP": 1417030.0,
            "GDPPC": 56341.94,
            "Population": 25.151
        }
    }
}